pymongoRawQuery/__init__.py
pymongoRawQuery/conditional_query.py
pymongoRawQuery/conn.py
pymongoRawQuery/exceptions.py
pymongoRawQuery/filter_database.py
pymongoRawQuery/filter_set.py
pymongoRawQuery/pymongoRawQuery.py
pymongoRawQuery/raw_query.py
pymongoRawQuery/utils.py
pymongoRawQuery/verify_nosql.py
pymongoRawQuery-1.0.0.dist-info/LICENSE
pymongoRawQuery-1.0.0.dist-info/METADATA
pymongoRawQuery-1.0.0.dist-info/WHEEL
pymongoRawQuery-1.0.0.dist-info/top_level.txt
pymongoRawQuery-1.0.0.dist-info/RECORD
