Metadata-Version: 2.1
Name: pymongoRawQuery
Version: 1.0.0
Summary: 支持mongodb原生语句安全查询数据，拆分校验nosql语句并查询数据（支持find、findOne、sort、limit、skip等一些查询关键字，自动过滤敏感数据库集合以及相应的关键字）
Home-page: https://github.com/YiZhang-You/pymongoRawQuery.git
Author: YiZhang-You
Author-email: yyz18071720400@163.com
Requires-Python: >=3.1
License-File: LICENSE
Requires-Dist: pymongo (>=4.0.1)
